reduction/__init__.py
reduction/algol_h_alpha_line_model.py
reduction/commandline.py
reduction/constants.py
reduction/fitgauss.py
reduction/fittable_spectrum.py
reduction/instrument.py
reduction/nan_statistics.py
reduction/normalize.py
reduction/observers.py
reduction/plot_radial_velocity.py
reduction/plotting.py
reduction/spectrum.py
reduction/scripts/__init__.py
reduction/scripts/display_fits_1d.py
reduction/scripts/display_fits_2d.py
reduction/scripts/fits_timeline.py
reduction/scripts/fitssetval.py
reduction/scripts/generate_report.py
reduction/scripts/helio.py
reduction/scripts/normalize_spectrum.py
reduction/scripts/plan_observations.py
reduction/scripts/star_altitude.py
reduction/stars/__init__.py
reduction/stars/algol.py
reduction/stars/binary_orbit.py
reduction/stars/delcep.py
reduction/stars/mizar.py
reduction/stars/variable_stars.py
reduction/utils/__init__.py
reduction/utils/display_h_alpha.py
reduction/utils/fit_h_alpha.py
reduction/utils/lebesgue.py
reduction/utils/ranges.py
algol_reduction-1.0.0b14.dist-info/METADATA
algol_reduction-1.0.0b14.dist-info/WHEEL
algol_reduction-1.0.0b14.dist-info/entry_points.txt
algol_reduction-1.0.0b14.dist-info/top_level.txt
algol_reduction-1.0.0b14.dist-info/RECORD
