Metadata-Version: 2.1
Name: algol-reduction
Version: 1.0.0b14
Summary: Spectral reduction package
Home-page: UNKNOWN
Author: Christian W. Brock
License: BSD
Platform: UNKNOWN
Classifier: Intended Audience :: Science/Research
Classifier: Topic :: Scientific/Engineering :: Astronomy
Classifier: Operating System :: OS Independent
Classifier: Programming Language :: Python :: 3
Classifier: License :: OSI Approved :: BSD License
Requires-Python: >=3.5
Requires-Dist: matplotlib
Requires-Dist: numpy
Requires-Dist: scipy (==1.4.1)
Requires-Dist: astropy (>=3.2.2)
Requires-Dist: astroplan (>=0.6)
Requires-Dist: icalendar
Provides-Extra: test
Requires-Dist: pytest ; extra == 'test'
